dbf2html/__init__.py
dbf2html/cli.py
dbf2html-0.0.2.dist-info/LICENSE
dbf2html-0.0.2.dist-info/METADATA
dbf2html-0.0.2.dist-info/WHEEL
dbf2html-0.0.2.dist-info/entry_points.txt
dbf2html-0.0.2.dist-info/top_level.txt
dbf2html-0.0.2.dist-info/RECORD
