Metadata-Version: 2.1
Name: dbf2html
Version: 0.0.2
Summary: UNKNOWN
Home-page: https://github.com/YangzhenZhao/dbf2html
Author: nocilantro
Author-email: UNKNOWN
License: UNKNOWN
Platform: UNKNOWN
Requires-Dist: click
Requires-Dist: dbfread
